sci_palettes/__init__.py
sci_palettes/palettes.py
sci_palettes/register.py
sci_palettes/version.json
sci_palettes/version.py
sci_palettes-1.0.1.dist-info/METADATA
sci_palettes-1.0.1.dist-info/WHEEL
sci_palettes-1.0.1.dist-info/top_level.txt
sci_palettes-1.0.1.dist-info/RECORD
