Metadata-Version: 2.1
Name: sci-palettes
Version: 1.0.1
Summary: sci palettes for matplotlib/seaborn
Home-page: https://github.com/suqingdong/sci_palettes
Author: suqingdong
Author-email: suqingdong1114@gmail.com
License: BSD License
Platform: UNKNOWN
Classifier: Development Status :: 5 - Production/Stable
Classifier: Operating System :: OS Independent
Classifier: Intended Audience :: Developers
Classifier: License :: OSI Approved :: BSD License
Classifier: Programming Language :: Python
Classifier: Programming Language :: Python :: 3
Classifier: Programming Language :: Python :: 3 :: Only
Classifier: Programming Language :: Python :: 3.8
Classifier: Topic :: Software Development :: Libraries
Requires-Dist: seaborn
Requires-Dist: matplotlib
